LICENSE.txt
pecs_framework/__init__.py
pecs_framework/_types.py
pecs_framework/base_system.py
pecs_framework/component.py
pecs_framework/domain.py
pecs_framework/engine.py
pecs_framework/entity.py
pecs_framework/events.py
pecs_framework/loader.py
pecs_framework/prefab.py
pecs_framework/query.py
pecs_framework/utils.py
README.md
pecs_framework-1.3.4.dist-info/LICENSE.txt
pecs_framework-1.3.4.dist-info/METADATA
pecs_framework-1.3.4.dist-info/WHEEL
pecs_framework-1.3.4.dist-info/RECORD
