Metadata-Version: 2.1
Name: pecs-framework
Version: 1.3.4
Summary: The ✨Respectably Muscled✨ Python Entity Component System
Home-page: https://github.com/krummja/PECS
Author: Jonathan Crum
Author-email: crumja4@gmail.com
Requires-Python: >=3.8, !=2.7.*, !=3.0.*, !=3.1.*, !=3.2.*, !=3.3.*, !=3.4.*, !=3.5.*, !=3.6.*, !=3.7.*
Classifier: License :: OSI Approved :: MIT License
Classifier: Operating System :: OS Independent
Classifier: Programming Language :: Python
Classifier: Programming Language :: Python :: 3
Classifier: Programming Language :: Python :: 3.8
Classifier: Programming Language :: Python :: 3.9
Classifier: Programming Language :: Python :: 3.10
Classifier: Programming Language :: Python :: 3.11
Classifier: Programming Language :: Python :: 3.12
Classifier: Programming Language :: Python :: Implementation :: CPython
Requires-Dist: beartype (>=0.17.2,<0.18.0)
Requires-Dist: deepmerge (==1.0.1)
Requires-Dist: numpy (>=1.23.4,<2.0.0)
Project-URL: Repository, https://github.com/krummja/PECS
